tensorboard/__init__.py
tensorboard/crc32c.py
tensorboard/embedding.py
tensorboard/event_file_writer.py
tensorboard/graph.py
tensorboard/record_writer.py
tensorboard/summary.py
tensorboard/writer.py
tensorboard/src/__init__.py
tensorboard/src/attr_value_pb2.py
tensorboard/src/event_pb2.py
tensorboard/src/graph_pb2.py
tensorboard/src/node_def_pb2.py
tensorboard/src/resource_handle_pb2.py
tensorboard/src/summary_pb2.py
tensorboard/src/tensor_pb2.py
tensorboard/src/tensor_shape_pb2.py
tensorboard/src/types_pb2.py
tensorboard/src/versions_pb2.py
tensorboard_pytorch-0.7.dist-info/DESCRIPTION.rst
tensorboard_pytorch-0.7.dist-info/METADATA
tensorboard_pytorch-0.7.dist-info/RECORD
tensorboard_pytorch-0.7.dist-info/WHEEL
tensorboard_pytorch-0.7.dist-info/metadata.json
tensorboard_pytorch-0.7.dist-info/top_level.txt
