Metadata-Version: 2.0
Name: tensorboard-pytorch
Version: 0.7
Summary: Log TensorBoard events with pytorch
Home-page: https://github.com/lanpa/tensorboard-pytorch
Author: Tzu-Wei Huang
Author-email: huang.dexter@gmail.com
License: MIT license
Platform: UNKNOWN
Classifier: Development Status :: 2 - Pre-Alpha
Classifier: Intended Audience :: Developers
Classifier: License :: OSI Approved :: MIT License
Classifier: Natural Language :: English
Classifier: Programming Language :: Python :: 2
Classifier: Programming Language :: Python :: 2.7
Classifier: Programming Language :: Python :: 3
Classifier: Programming Language :: Python :: 3.4
Classifier: Programming Language :: Python :: 3.5
Classifier: Programming Language :: Python :: 3.6
Requires-Dist: numpy
Requires-Dist: protobuf
Requires-Dist: six
